AmosLogger/AmosLogger.py
AmosLogger/AmosLoggerFormatter.py
AmosLogger/__init__.py
AmosLogger-0.0.3.dist-info/METADATA
AmosLogger-0.0.3.dist-info/WHEEL
AmosLogger-0.0.3.dist-info/top_level.txt
AmosLogger-0.0.3.dist-info/RECORD
