Metadata-Version: 2.1
Name: AmosLogger
Version: 0.0.3
Summary: Amos Logger
Home-page: https://github.com/bowofamos/amos_log#readme
Author: ganyu
Author-email: amosbow@163.com
